<?xml version="1.0"?>
<groundnet>
  <version>1</version>
  <parkingList>
        <Parking index="0" type="ga" name="General_Aviation_3" lat="N63 27.191284" lon="E10 55.530060" heading="-84.89"  radius="10" pushBackRoute="36" airlineCodes="" />
        <Parking index="1" type="gate" name="General_Aviation_6" lat="N63 27.106481" lon="E10 55.506328" heading="-16.39"  radius="10" pushBackRoute="38" airlineCodes="" />
        <Parking index="2" type="gate" name="General_Aviation_6" lat="N63 27.097856" lon="E10 55.461757" heading="14.2"  radius="10" pushBackRoute="39" airlineCodes="" />
        <Parking index="3" type="gate" name="General_Aviation_5" lat="N63 27.102533" lon="E10 55.485794" heading="-16.39"  radius="10" pushBackRoute="100" airlineCodes="" />
        <Parking index="4" type="gate" name="General_Aviation_4" lat="N63 27.198849" lon="E10 55.538855" heading="-84.89"  radius="10" pushBackRoute="36" airlineCodes="" />
        <Parking index="5" type="gate" name="General_Aviation_2" lat="N63 27.182485" lon="E10 55.539004" heading="-84.89"  radius="10" pushBackRoute="37" airlineCodes="" />
        <Parking index="6" type="gate" name="General_Aviation_1" lat="N63 27.180154" lon="E10 55.496909" heading="180.84"  radius="10" pushBackRoute="36" airlineCodes="" />
        <Parking index="7" type="gate" name="Gate_38" lat="N63 27.323865" lon="E10 55.248423" heading="179.49"  radius="18" pushBackRoute="64" airlineCodes="WIF,SAS,NAX" />
        <Parking index="8" type="gate" name="Gate_39" lat="N63 27.321877" lon="E10 55.312346" heading="135.56"  radius="18" pushBackRoute="65" airlineCodes="WIF,SAS,NAX" />
        <Parking index="9" type="gate" name="Gate_22" lat="N63 27.132905" lon="E10 54.766766" heading="89.69"  radius="18" pushBackRoute="88" airlineCodes="DTR,WIF" />
        <Parking index="10" type="gate" name="Gate_23" lat="N63 27.155513" lon="E10 54.767094" heading="89.69"  radius="18" pushBackRoute="49" airlineCodes="DTR,WIF" />
        <Parking index="11" type="gate" name="Gate_24" lat="N63 27.179726" lon="E10 54.767445" heading="89.69"  radius="18" pushBackRoute="48" airlineCodes="DTR,WIF" />
        <Parking index="12" type="gate" name="Gate_25" lat="N63 27.203270" lon="E10 54.767787" heading="89.69"  radius="18" pushBackRoute="47" airlineCodes="DTR,WIF" />
        <Parking index="13" type="gate" name="Gate_26" lat="N63 27.226146" lon="E10 54.768119" heading="89.69"  radius="18" pushBackRoute="46" airlineCodes="DTR,WIF" />
        <Parking index="14" type="gate" name="Gate_27" lat="N63 27.251066" lon="E10 54.768480" heading="89.69"  radius="18" pushBackRoute="45" airlineCodes="DTR,WIF" />
        <Parking index="15" type="gate" name="Gate_28" lat="N63 27.272837" lon="E10 54.768796" heading="89.69"  radius="18" pushBackRoute="44" airlineCodes="DTR,WIF" />
        <Parking index="16" type="gate" name="Gate_29" lat="N63 27.297809" lon="E10 54.780974" heading="89.69"  radius="18" pushBackRoute="50" airlineCodes="DTR,WIF" />
        <Parking index="17" type="gate" name="Gate_30" lat="N63 27.302457" lon="E10 54.821998" heading="179.77"  radius="20" pushBackRoute="93" airlineCodes="WIF,SAS,NAX" />
        <Parking index="18" type="gate" name="Gate_31" lat="N63 27.302370" lon="E10 54.889773" heading="-179.84"  radius="20" pushBackRoute="94" airlineCodes="WIF,SAS,NAX" />
        <Parking index="19" type="gate" name="Gate_32" lat="N63 27.302296" lon="E10 54.948218" heading="-179.57"  radius="20" pushBackRoute="95" airlineCodes="WIF,SAS,NAX" />
        <Parking index="20" type="gate" name="Gate_33" lat="N63 27.302234" lon="E10 54.996816" heading="-179.57"  radius="20" pushBackRoute="96" airlineCodes="WIF,SAS,NAX" />
        <Parking index="21" type="gate" name="Gate_34" lat="N63 27.302172" lon="E10 55.044867" heading="-179.61"  radius="20" pushBackRoute="97" airlineCodes="WIF,SAS,NAX" />
        <Parking index="22" type="gate" name="Gate_35" lat="N63 27.302110" lon="E10 55.093295" heading="-179.62"  radius="20" pushBackRoute="98" airlineCodes="WIF,SAS,NAX" />
        <Parking index="23" type="gate" name="Gate_36" lat="N63 27.302046" lon="E10 55.143271" heading="179.56"  radius="20" pushBackRoute="99" airlineCodes="WIF,SAS,NAX" />
        <Parking index="24" type="gate" name="M6" lat="N63 27.572124" lon="E10 55.223676" heading="-142.42"  radius="36" pushBackRoute="84" airlineCodes="" />
        <Parking index="25" type="gate" name="M5" lat="N63 27.572109" lon="E10 55.102206" heading="-142.42"  radius="36" pushBackRoute="76" airlineCodes="" />
        <Parking index="26" type="gate" name="M4" lat="N63 27.575682" lon="E10 54.986151" heading="-142.42"  radius="36" pushBackRoute="82" airlineCodes="TAY" />
        <Parking index="27" type="gate" name="Gate_37" lat="N63 27.301977" lon="E10 55.197609" heading="179.56"  radius="20" pushBackRoute="87" airlineCodes="WIF,SAS,NAX" />
        <Parking index="28" type="gate" name="Gate_40" lat="N63 27.307110" lon="E10 55.361610" heading="-89.27"  radius="20" pushBackRoute="102" airlineCodes="SAS,NAX,EVE,ICE,KLM,LOT,OAE,WZZ,SWN,VKG" />
        <Parking index="29" type="gate" name="Gate_41" lat="N63 27.282098" lon="E10 55.355342" heading="-89.27"  radius="20" pushBackRoute="73" airlineCodes="EVE,ICE,KLM,LOT,OAE,WZZ,SWN,VKG" />
        <Parking index="30" type="gate" name="Gate_42" lat="N63 27.255825" lon="E10 55.352506" heading="-89.27"  radius="20" pushBackRoute="72" airlineCodes="EVE,ICE,KLM,LOT,OAE,WZZ,SWN,VKG" />
        <Parking index="31" type="gate" name="Gate_43" lat="N63 27.231654" lon="E10 55.353036" heading="-89.27"  radius="20" pushBackRoute="71" airlineCodes="EVE,ICE,KLM,LOT,OAE,WZZ,SWN,VKG" />
        <Parking index="32" type="gate" name="Gate_44" lat="N63 27.207156" lon="E10 55.353573" heading="-89.27"  radius="20" pushBackRoute="70" airlineCodes="EVE,ICE,KLM,LOT,OAE,WZZ,SWN,VKG" />
        <Parking index="33" type="gate" name="Gate_45" lat="N63 27.183176" lon="E10 55.354099" heading="-89.27"  radius="20" pushBackRoute="69" airlineCodes="EVE,ICE,KLM,LOT,OAE,WZZ,SWN,VKG" />
 </parkingList>
 <TaxiNodes>
        <node index="34" lat="N63 27.122711" lon="E10 55.288933" isOnRunway="0" holdPointType="none"  />
        <node index="35" lat="N63 27.136983" lon="E10 55.345104" isOnRunway="0" holdPointType="none"  />
        <node index="36" lat="N63 27.202477" lon="E10 55.512203" isOnRunway="0" holdPointType="PushBack"  />
        <node index="37" lat="N63 27.173210" lon="E10 55.512202" isOnRunway="0" holdPointType="PushBack"  />
        <node index="38" lat="N63 27.121724" lon="E10 55.508872" isOnRunway="0" holdPointType="PushBack"  />
        <node index="39" lat="N63 27.116201" lon="E10 55.464536" isOnRunway="0" holdPointType="PushBack"  />
        <node index="40" lat="N63 27.148982" lon="E10 55.448687" isOnRunway="0" holdPointType="none"  />
        <node index="41" lat="N63 27.150020" lon="E10 55.332837" isOnRunway="0" holdPointType="none"  />
        <node index="42" lat="N63 27.149909" lon="E10 55.345104" isOnRunway="0" holdPointType="none"  />
        <node index="43" lat="N63 27.124937" lon="E10 54.790621" isOnRunway="0" holdPointType="none"  />
        <node index="44" lat="N63 27.275341" lon="E10 54.791029" isOnRunway="0" holdPointType="PushBack"  />
        <node index="45" lat="N63 27.251444" lon="E10 54.790808" isOnRunway="0" holdPointType="PushBack"  />
        <node index="46" lat="N63 27.226266" lon="E10 54.790326" isOnRunway="0" holdPointType="PushBack"  />
        <node index="47" lat="N63 27.203455" lon="E10 54.790085" isOnRunway="0" holdPointType="PushBack"  />
        <node index="48" lat="N63 27.180322" lon="E10 54.790326" isOnRunway="0" holdPointType="PushBack"  />
        <node index="49" lat="N63 27.155789" lon="E10 54.790325" isOnRunway="0" holdPointType="PushBack"  />
        <node index="50" lat="N63 27.277753" lon="E10 54.792535" isOnRunway="0" holdPointType="PushBack"  />
        <node index="51" lat="N63 27.279134" lon="E10 54.796064" isOnRunway="0" holdPointType="none"  />
        <node index="52" lat="N63 27.279904" lon="E10 54.801903" isOnRunway="0" holdPointType="none"  />
        <node index="53" lat="N63 27.278603" lon="E10 55.221588" isOnRunway="0" holdPointType="none"  />
        <node index="54" lat="N63 27.278625" lon="E10 55.198045" isOnRunway="0" holdPointType="none"  />
        <node index="55" lat="N63 27.278849" lon="E10 55.140866" isOnRunway="0" holdPointType="none"  />
        <node index="56" lat="N63 27.278924" lon="E10 55.092046" isOnRunway="0" holdPointType="none"  />
        <node index="57" lat="N63 27.279148" lon="E10 55.044062" isOnRunway="0" holdPointType="none"  />
        <node index="58" lat="N63 27.279223" lon="E10 54.995410" isOnRunway="0" holdPointType="none"  />
        <node index="59" lat="N63 27.279447" lon="E10 54.946088" isOnRunway="0" holdPointType="none"  />
        <node index="60" lat="N63 27.279522" lon="E10 54.890915" isOnRunway="0" holdPointType="none"  />
        <node index="61" lat="N63 27.279970" lon="E10 54.818354" isOnRunway="0" holdPointType="none"  />
        <node index="62" lat="N63 27.282824" lon="E10 55.232547" isOnRunway="0" holdPointType="none"  />
        <node index="63" lat="N63 27.302750" lon="E10 55.234057" isOnRunway="0" holdPointType="none"  />
        <node index="64" lat="N63 27.305188" lon="E10 55.242300" isOnRunway="0" holdPointType="PushBack"  />
        <node index="65" lat="N63 27.304981" lon="E10 55.293619" isOnRunway="0" holdPointType="PushBack"  />
        <node index="66" lat="N63 27.302438" lon="E10 55.310222" isOnRunway="0" holdPointType="none"  />
        <node index="67" lat="N63 27.294734" lon="E10 55.320366" isOnRunway="0" holdPointType="none"  />
        <node index="68" lat="N63 27.168972" lon="E10 55.319375" isOnRunway="0" holdPointType="none"  />
        <node index="69" lat="N63 27.182878" lon="E10 55.319567" isOnRunway="0" holdPointType="PushBack"  />
        <node index="70" lat="N63 27.207287" lon="E10 55.319984" isOnRunway="0" holdPointType="PushBack"  />
        <node index="71" lat="N63 27.232316" lon="E10 55.320281" isOnRunway="0" holdPointType="PushBack"  />
        <node index="72" lat="N63 27.256254" lon="E10 55.320208" isOnRunway="0" holdPointType="PushBack"  />
        <node index="73" lat="N63 27.282092" lon="E10 55.320384" isOnRunway="0" holdPointType="PushBack"  />
        <node index="74" lat="N63 27.160850" lon="E10 55.237077" isOnRunway="0" holdPointType="none"  />
        <node index="75" lat="N63 27.161819" lon="E10 55.153541" isOnRunway="0" holdPointType="none"  />
        <node index="76" lat="N63 27.623459" lon="E10 55.092890" isOnRunway="0" holdPointType="PushBack"  />
        <node index="77" lat="N63 27.620599" lon="E10 55.403445" isOnRunway="0" holdPointType="none"  />
        <node index="78" lat="N63 27.623455" lon="E10 55.374394" isOnRunway="0" holdPointType="none"  />
        <node index="79" lat="N63 27.608833" lon="E10 55.437068" isOnRunway="0" holdPointType="none"  />
        <node index="80" lat="N63 27.588804" lon="E10 55.455228" isOnRunway="0" holdPointType="none"  />
        <node index="81" lat="N63 27.526316" lon="E10 54.953227" isOnRunway="0" holdPointType="none"  />
        <node index="82" lat="N63 27.538322" lon="E10 54.996931" isOnRunway="0" holdPointType="PushBack"  />
        <node index="83" lat="N63 27.537838" lon="E10 55.145392" isOnRunway="0" holdPointType="none"  />
        <node index="84" lat="N63 27.551733" lon="E10 55.193977" isOnRunway="0" holdPointType="PushBack"  />
        <node index="85" lat="N63 27.506073" lon="E10 54.928677" isOnRunway="0" holdPointType="none"  />
        <node index="86" lat="N63 27.504340" lon="E10 55.454516" isOnRunway="0" holdPointType="none"  />
        <node index="87" lat="N63 27.334157" lon="E10 55.198881" isOnRunway="0" holdPointType="PushBack"  />
        <node index="88" lat="N63 27.132200" lon="E10 54.685415" isOnRunway="0" holdPointType="PushBack"  />
        <node index="89" lat="N63 27.179374" lon="E10 54.685826" isOnRunway="0" holdPointType="none"  />
        <node index="90" lat="N63 27.225492" lon="E10 54.686042" isOnRunway="0" holdPointType="none"  />
        <node index="91" lat="N63 27.272904" lon="E10 54.686042" isOnRunway="0" holdPointType="none"  />
        <node index="92" lat="N63 27.335873" lon="E10 54.686451" isOnRunway="0" holdPointType="none"  />
        <node index="93" lat="N63 27.335438" lon="E10 54.821843" isOnRunway="0" holdPointType="PushBack"  />
        <node index="94" lat="N63 27.335238" lon="E10 54.890497" isOnRunway="0" holdPointType="PushBack"  />
        <node index="95" lat="N63 27.334976" lon="E10 54.948942" isOnRunway="0" holdPointType="PushBack"  />
        <node index="96" lat="N63 27.334743" lon="E10 54.997117" isOnRunway="0" holdPointType="PushBack"  />
        <node index="97" lat="N63 27.334604" lon="E10 55.046231" isOnRunway="0" holdPointType="PushBack"  />
        <node index="98" lat="N63 27.334453" lon="E10 55.095163" isOnRunway="0" holdPointType="PushBack"  />
        <node index="99" lat="N63 27.334250" lon="E10 55.144289" isOnRunway="0" holdPointType="PushBack"  />
        <node index="100" lat="N63 27.121423" lon="E10 55.485637" isOnRunway="0" holdPointType="PushBack"  />
        <node index="101" lat="N63 27.333263" lon="E10 55.452866" isOnRunway="0" holdPointType="none"  />
        <node index="102" lat="N63 27.304948" lon="E10 55.460012" isOnRunway="0" holdPointType="PushBack"  />
        <node index="103" lat="N63 27.169690" lon="E10 55.459294" isOnRunway="0" holdPointType="none"  />
        <node index="104" lat="N63 27.206861" lon="E10 55.460016" isOnRunway="0" holdPointType="none"  />
        <node index="105" lat="N63 27.255112" lon="E10 55.459738" isOnRunway="0" holdPointType="none"  />
        <node index="106" lat="N63 27.378389" lon="E10 54.225226" isOnRunway="0" holdPointType="none"  />
        <node index="107" lat="N63 27.359775" lon="E10 53.594108" isOnRunway="0" holdPointType="none"  />
        <node index="108" lat="N63 27.373362" lon="E10 53.566814" isOnRunway="0" holdPointType="none"  />
        <node index="109" lat="N63 27.367700" lon="E10 56.324218" isOnRunway="0" holdPointType="none"  />
        <node index="110" lat="N63 27.355223" lon="E10 56.255108" isOnRunway="0" holdPointType="none"  />
        <node index="111" lat="N63 27.360212" lon="E10 56.293574" isOnRunway="0" holdPointType="none"  />
        <node index="112" lat="N63 27.361381" lon="E10 53.328620" isOnRunway="0" holdPointType="none"  />
        <node index="113" lat="N63 27.360827" lon="E10 53.591996" isOnRunway="0" holdPointType="none"  />
        <node index="114" lat="N63 27.360497" lon="E10 53.753068" isOnRunway="0" holdPointType="none"  />
        <node index="115" lat="N63 27.359447" lon="E10 54.235076" isOnRunway="0" holdPointType="none"  />
        <node index="116" lat="N63 27.358553" lon="E10 54.686735" isOnRunway="0" holdPointType="none"  />
        <node index="117" lat="N63 27.358449" lon="E10 54.821246" isOnRunway="0" holdPointType="none"  />
        <node index="118" lat="N63 27.358115" lon="E10 54.890803" isOnRunway="0" holdPointType="none"  />
        <node index="119" lat="N63 27.358095" lon="E10 54.910889" isOnRunway="0" holdPointType="none"  />
        <node index="120" lat="N63 27.357914" lon="E10 54.949384" isOnRunway="0" holdPointType="none"  />
        <node index="121" lat="N63 27.357878" lon="E10 54.997053" isOnRunway="0" holdPointType="none"  />
        <node index="122" lat="N63 27.357776" lon="E10 55.046973" isOnRunway="0" holdPointType="none"  />
        <node index="123" lat="N63 27.357641" lon="E10 55.096198" isOnRunway="0" holdPointType="none"  />
        <node index="124" lat="N63 27.357456" lon="E10 55.145222" isOnRunway="0" holdPointType="none"  />
        <node index="125" lat="N63 27.357515" lon="E10 55.199534" isOnRunway="0" holdPointType="none"  />
        <node index="126" lat="N63 27.356913" lon="E10 55.453048" isOnRunway="0" holdPointType="none"  />
        <node index="127" lat="N63 27.364803" lon="E10 53.304088" isOnRunway="0" holdPointType="none"  />
        <node index="128" lat="N63 27.374875" lon="E10 53.265731" isOnRunway="0" holdPointType="none"  />
        <node index="129" lat="N63 27.391667" lon="E10 53.225473" isOnRunway="0" holdPointType="none"  />
        <node index="130" lat="N63 27.442709" lon="E10 56.487054" isOnRunway="0" holdPointType="none"  />
        <node index="131" lat="N63 27.401921" lon="E10 56.398325" isOnRunway="0" holdPointType="none"  />
        <node index="132" lat="N63 27.407826" lon="E10 55.453672" isOnRunway="0" holdPointType="none"  />
        <node index="133" lat="N63 27.408617" lon="E10 54.910208" isOnRunway="0" holdPointType="none"  />
        <node index="134" lat="N63 27.436685" lon="E10 54.300133" isOnRunway="0" holdPointType="none"  />
        <node index="135" lat="N63 27.419909" lon="E10 54.249697" isOnRunway="0" holdPointType="none"  />
        <node index="136" lat="N63 27.405248" lon="E10 54.231484" isOnRunway="0" holdPointType="none"  />
        <node index="137" lat="N63 27.387319" lon="E10 53.679449" isOnRunway="0" holdPointType="none"  />
        <node index="138" lat="N63 27.385825" lon="E10 53.560468" isOnRunway="0" holdPointType="none"  />
        <node index="139" lat="N63 27.430906" lon="E10 53.560684" isOnRunway="0" holdPointType="none"  />
        <node index="140" lat="N63 27.411211" lon="E10 53.207688" isOnRunway="0" holdPointType="none"  />
        <node index="141" lat="N63 27.453778" lon="E10 56.485751" isOnRunway="1" holdPointType="none"  />
        <node index="142" lat="N63 27.459716" lon="E10 53.206832" isOnRunway="1" holdPointType="none"  />
        <node index="143" lat="N63 27.459096" lon="E10 53.560996" isOnRunway="1" holdPointType="none"  />
        <node index="144" lat="N63 27.457607" lon="E10 54.455667" isOnRunway="1" holdPointType="none"  />
        <node index="145" lat="N63 27.456625" lon="E10 54.909572" isOnRunway="1" holdPointType="none"  />
        <node index="146" lat="N63 27.456517" lon="E10 54.928030" isOnRunway="1" holdPointType="none"  />
        <node index="147" lat="N63 27.455675" lon="E10 55.454356" isOnRunway="1" holdPointType="none"  />
        <node index="148" lat="N63 27.188868" lon="E10 55.557077" isOnRunway="0" holdPointType="none"  />
        <node index="149" lat="N63 27.080458" lon="E10 55.513982" isOnRunway="0" holdPointType="none"  />
        <node index="150" lat="N63 27.071560" lon="E10 55.455103" isOnRunway="0" holdPointType="none"  />
        <node index="151" lat="N63 27.076510" lon="E10 55.493448" isOnRunway="0" holdPointType="none"  />
        <node index="152" lat="N63 27.196433" lon="E10 55.565872" isOnRunway="0" holdPointType="none"  />
        <node index="153" lat="N63 27.180070" lon="E10 55.566021" isOnRunway="0" holdPointType="none"  />
        <node index="154" lat="N63 27.207276" lon="E10 55.497307" isOnRunway="0" holdPointType="none"  />
        <node index="155" lat="N63 27.350989" lon="E10 55.248181" isOnRunway="0" holdPointType="none"  />
        <node index="156" lat="N63 27.341244" lon="E10 55.293355" isOnRunway="0" holdPointType="none"  />
        <node index="157" lat="N63 27.132758" lon="E10 54.739642" isOnRunway="0" holdPointType="none"  />
        <node index="158" lat="N63 27.155366" lon="E10 54.739970" isOnRunway="0" holdPointType="none"  />
        <node index="159" lat="N63 27.179579" lon="E10 54.740321" isOnRunway="0" holdPointType="none"  />
        <node index="160" lat="N63 27.203123" lon="E10 54.740662" isOnRunway="0" holdPointType="none"  />
        <node index="161" lat="N63 27.225999" lon="E10 54.740994" isOnRunway="0" holdPointType="none"  />
        <node index="162" lat="N63 27.250919" lon="E10 54.741356" isOnRunway="0" holdPointType="none"  />
        <node index="163" lat="N63 27.272690" lon="E10 54.741672" isOnRunway="0" holdPointType="none"  />
        <node index="164" lat="N63 27.297662" lon="E10 54.753850" isOnRunway="0" holdPointType="none"  />
        <node index="165" lat="N63 27.329582" lon="E10 54.821889" isOnRunway="0" holdPointType="none"  />
        <node index="166" lat="N63 27.329495" lon="E10 54.889848" isOnRunway="0" holdPointType="none"  />
        <node index="167" lat="N63 27.329420" lon="E10 54.948421" isOnRunway="0" holdPointType="none"  />
        <node index="168" lat="N63 27.329358" lon="E10 54.997020" isOnRunway="0" holdPointType="none"  />
        <node index="169" lat="N63 27.329296" lon="E10 55.045052" isOnRunway="0" holdPointType="none"  />
        <node index="170" lat="N63 27.329235" lon="E10 55.093475" isOnRunway="0" holdPointType="none"  />
        <node index="171" lat="N63 27.329170" lon="E10 55.143063" isOnRunway="0" holdPointType="none"  />
        <node index="172" lat="N63 27.593621" lon="E10 55.240218" isOnRunway="0" holdPointType="none"  />
        <node index="173" lat="N63 27.593606" lon="E10 55.118748" isOnRunway="0" holdPointType="none"  />
        <node index="174" lat="N63 27.597179" lon="E10 55.002694" isOnRunway="0" holdPointType="none"  />
        <node index="175" lat="N63 27.329101" lon="E10 55.197401" isOnRunway="0" holdPointType="none"  />
        <node index="176" lat="N63 27.306765" lon="E10 55.388733" isOnRunway="0" holdPointType="none"  />
        <node index="177" lat="N63 27.281753" lon="E10 55.382465" isOnRunway="0" holdPointType="none"  />
        <node index="178" lat="N63 27.255480" lon="E10 55.379628" isOnRunway="0" holdPointType="none"  />
        <node index="179" lat="N63 27.231308" lon="E10 55.380158" isOnRunway="0" holdPointType="none"  />
        <node index="180" lat="N63 27.206811" lon="E10 55.380695" isOnRunway="0" holdPointType="none"  />
        <node index="181" lat="N63 27.182831" lon="E10 55.381221" isOnRunway="0" holdPointType="none"  />
 </TaxiNodes>
 <TaxiWaySegments>
        <arc begin="99" end="124" isPushBackRoute="0" name=""  />
        <arc begin="124" end="99" isPushBackRoute="0" name=""  />
        <arc begin="98" end="123" isPushBackRoute="0" name=""  />
        <arc begin="123" end="98" isPushBackRoute="0" name=""  />
        <arc begin="97" end="122" isPushBackRoute="0" name=""  />
        <arc begin="122" end="97" isPushBackRoute="0" name=""  />
        <arc begin="96" end="121" isPushBackRoute="0" name=""  />
        <arc begin="121" end="96" isPushBackRoute="0" name=""  />
        <arc begin="95" end="120" isPushBackRoute="0" name=""  />
        <arc begin="120" end="95" isPushBackRoute="0" name=""  />
        <arc begin="94" end="118" isPushBackRoute="0" name=""  />
        <arc begin="118" end="94" isPushBackRoute="0" name=""  />
        <arc begin="93" end="117" isPushBackRoute="0" name=""  />
        <arc begin="117" end="93" isPushBackRoute="0" name=""  />
        <arc begin="77" end="78" isPushBackRoute="0" name="B2"  />
        <arc begin="78" end="76" isPushBackRoute="0" name="B2"  />
        <arc begin="79" end="77" isPushBackRoute="0" name="B2"  />
        <arc begin="80" end="79" isPushBackRoute="0" name="B2"  />
        <arc begin="86" end="80" isPushBackRoute="0" name="B2"  />
        <arc begin="81" end="85" isPushBackRoute="0" name="B1"  />
        <arc begin="82" end="81" isPushBackRoute="0" name="B1"  />
        <arc begin="83" end="82" isPushBackRoute="0" name="B1"  />
        <arc begin="84" end="83" isPushBackRoute="0" name="B1"  />
        <arc begin="85" end="146" isPushBackRoute="0" name="B1"  />
        <arc begin="147" end="86" isPushBackRoute="0" name="B2"  />
        <arc begin="87" end="125" isPushBackRoute="0" name="W"  />
        <arc begin="125" end="87" isPushBackRoute="0" name="W"  />
        <arc begin="92" end="93" isPushBackRoute="0" name="W"  />
        <arc begin="93" end="92" isPushBackRoute="0" name="W"  />
        <arc begin="93" end="94" isPushBackRoute="0" name="W"  />
        <arc begin="94" end="93" isPushBackRoute="0" name="W"  />
        <arc begin="94" end="95" isPushBackRoute="0" name="W"  />
        <arc begin="95" end="94" isPushBackRoute="0" name="W"  />
        <arc begin="95" end="96" isPushBackRoute="0" name="W"  />
        <arc begin="96" end="95" isPushBackRoute="0" name="W"  />
        <arc begin="96" end="97" isPushBackRoute="0" name="W"  />
        <arc begin="97" end="96" isPushBackRoute="0" name="W"  />
        <arc begin="97" end="98" isPushBackRoute="0" name="W"  />
        <arc begin="98" end="97" isPushBackRoute="0" name="W"  />
        <arc begin="98" end="99" isPushBackRoute="0" name="W"  />
        <arc begin="99" end="98" isPushBackRoute="0" name="W"  />
        <arc begin="99" end="87" isPushBackRoute="0" name="W"  />
        <arc begin="87" end="99" isPushBackRoute="0" name="W"  />
        <arc begin="88" end="89" isPushBackRoute="0" name="H"  />
        <arc begin="89" end="88" isPushBackRoute="0" name="H"  />
        <arc begin="89" end="90" isPushBackRoute="0" name="H"  />
        <arc begin="90" end="89" isPushBackRoute="0" name="H"  />
        <arc begin="90" end="91" isPushBackRoute="0" name="H"  />
        <arc begin="91" end="90" isPushBackRoute="0" name="H"  />
        <arc begin="91" end="92" isPushBackRoute="0" name="H"  />
        <arc begin="92" end="91" isPushBackRoute="0" name="H"  />
        <arc begin="92" end="116" isPushBackRoute="0" name="H"  />
        <arc begin="116" end="92" isPushBackRoute="0" name="H"  />
        <arc begin="103" end="100" isPushBackRoute="0" name="J"  />
        <arc begin="100" end="103" isPushBackRoute="0" name="J"  />
        <arc begin="101" end="126" isPushBackRoute="0" name="J"  />
        <arc begin="126" end="101" isPushBackRoute="0" name="J"  />
        <arc begin="102" end="101" isPushBackRoute="0" name="J"  />
        <arc begin="101" end="102" isPushBackRoute="0" name="J"  />
        <arc begin="103" end="104" isPushBackRoute="0" name="J"  />
        <arc begin="104" end="103" isPushBackRoute="0" name="J"  />
        <arc begin="104" end="105" isPushBackRoute="0" name="J"  />
        <arc begin="105" end="104" isPushBackRoute="0" name="J"  />
        <arc begin="105" end="102" isPushBackRoute="0" name="J"  />
        <arc begin="102" end="105" isPushBackRoute="0" name="J"  />
        <arc begin="132" end="126" isPushBackRoute="0" name="A6"  />
        <arc begin="126" end="132" isPushBackRoute="0" name="A6"  />
        <arc begin="133" end="119" isPushBackRoute="0" name="A5"  />
        <arc begin="119" end="133" isPushBackRoute="0" name="A5"  />
        <arc begin="106" end="115" isPushBackRoute="0" name="A4"  />
        <arc begin="115" end="106" isPushBackRoute="0" name="A4"  />
        <arc begin="136" end="106" isPushBackRoute="0" name="A4"  />
        <arc begin="106" end="136" isPushBackRoute="0" name="A4"  />
        <arc begin="137" end="114" isPushBackRoute="0" name="A3"  />
        <arc begin="114" end="137" isPushBackRoute="0" name="A3"  />
        <arc begin="108" end="113" isPushBackRoute="0" name="A2"  />
        <arc begin="113" end="108" isPushBackRoute="0" name="A2"  />
        <arc begin="113" end="107" isPushBackRoute="0" name="A2"  />
        <arc begin="107" end="113" isPushBackRoute="0" name="A2"  />
        <arc begin="138" end="108" isPushBackRoute="0" name="A2"  />
        <arc begin="108" end="138" isPushBackRoute="0" name="A2"  />
        <arc begin="109" end="131" isPushBackRoute="0" name="Y"  />
        <arc begin="131" end="109" isPushBackRoute="0" name="Y"  />
        <arc begin="110" end="111" isPushBackRoute="0" name="Y"  />
        <arc begin="111" end="110" isPushBackRoute="0" name="Y"  />
        <arc begin="111" end="109" isPushBackRoute="0" name="Y"  />
        <arc begin="109" end="111" isPushBackRoute="0" name="Y"  />
        <arc begin="112" end="113" isPushBackRoute="0" name="Y"  />
        <arc begin="113" end="112" isPushBackRoute="0" name="Y"  />
        <arc begin="113" end="114" isPushBackRoute="0" name="Y"  />
        <arc begin="114" end="113" isPushBackRoute="0" name="Y"  />
        <arc begin="114" end="115" isPushBackRoute="0" name="Y"  />
        <arc begin="115" end="114" isPushBackRoute="0" name="Y"  />
        <arc begin="115" end="116" isPushBackRoute="0" name="Y"  />
        <arc begin="116" end="115" isPushBackRoute="0" name="Y"  />
        <arc begin="116" end="117" isPushBackRoute="0" name="Y"  />
        <arc begin="117" end="116" isPushBackRoute="0" name="Y"  />
        <arc begin="117" end="118" isPushBackRoute="0" name="Y"  />
        <arc begin="118" end="117" isPushBackRoute="0" name="Y"  />
        <arc begin="118" end="119" isPushBackRoute="0" name="Y"  />
        <arc begin="119" end="118" isPushBackRoute="0" name="Y"  />
        <arc begin="119" end="120" isPushBackRoute="0" name="Y"  />
        <arc begin="120" end="119" isPushBackRoute="0" name="Y"  />
        <arc begin="120" end="121" isPushBackRoute="0" name="Y"  />
        <arc begin="121" end="120" isPushBackRoute="0" name="Y"  />
        <arc begin="121" end="122" isPushBackRoute="0" name="Y"  />
        <arc begin="122" end="121" isPushBackRoute="0" name="Y"  />
        <arc begin="122" end="123" isPushBackRoute="0" name="Y"  />
        <arc begin="123" end="122" isPushBackRoute="0" name="Y"  />
        <arc begin="123" end="124" isPushBackRoute="0" name="Y"  />
        <arc begin="124" end="123" isPushBackRoute="0" name="Y"  />
        <arc begin="124" end="125" isPushBackRoute="0" name="Y"  />
        <arc begin="125" end="124" isPushBackRoute="0" name="Y"  />
        <arc begin="125" end="126" isPushBackRoute="0" name="Y"  />
        <arc begin="126" end="125" isPushBackRoute="0" name="Y"  />
        <arc begin="126" end="110" isPushBackRoute="0" name="Y"  />
        <arc begin="110" end="126" isPushBackRoute="0" name="Y"  />
        <arc begin="127" end="112" isPushBackRoute="0" name="Y"  />
        <arc begin="112" end="127" isPushBackRoute="0" name="Y"  />
        <arc begin="128" end="127" isPushBackRoute="0" name="Y"  />
        <arc begin="127" end="128" isPushBackRoute="0" name="Y"  />
        <arc begin="129" end="128" isPushBackRoute="0" name="Y"  />
        <arc begin="128" end="129" isPushBackRoute="0" name="Y"  />
        <arc begin="140" end="129" isPushBackRoute="0" name="Y"  />
        <arc begin="129" end="140" isPushBackRoute="0" name="Y"  />
        <arc begin="130" end="141" isPushBackRoute="0" name="A8"  />
        <arc begin="141" end="130" isPushBackRoute="0" name="A8"  />
        <arc begin="131" end="130" isPushBackRoute="0" name="A8"  />
        <arc begin="130" end="131" isPushBackRoute="0" name="A8"  />
        <arc begin="132" end="147" isPushBackRoute="0" name="A6"  />
        <arc begin="147" end="132" isPushBackRoute="0" name="A6"  />
        <arc begin="133" end="145" isPushBackRoute="0" name="A5"  />
        <arc begin="145" end="133" isPushBackRoute="0" name="A5"  />
        <arc begin="134" end="144" isPushBackRoute="0" name="A4"  />
        <arc begin="144" end="134" isPushBackRoute="0" name="A4"  />
        <arc begin="135" end="134" isPushBackRoute="0" name="A4"  />
        <arc begin="134" end="135" isPushBackRoute="0" name="A4"  />
        <arc begin="136" end="135" isPushBackRoute="0" name="A4"  />
        <arc begin="135" end="136" isPushBackRoute="0" name="A4"  />
        <arc begin="137" end="139" isPushBackRoute="0" name="A3"  />
        <arc begin="139" end="137" isPushBackRoute="0" name="A3"  />
        <arc begin="138" end="139" isPushBackRoute="0" name="A2"  />
        <arc begin="139" end="138" isPushBackRoute="0" name="A2"  />
        <arc begin="139" end="143" isPushBackRoute="0" name="A2"  />
        <arc begin="143" end="139" isPushBackRoute="0" name="A2"  />
        <arc begin="140" end="142" isPushBackRoute="0" name="A1"  />
        <arc begin="142" end="140" isPushBackRoute="0" name="A1"  />
        <arc begin="0" end="148" isPushBackRoute="1" name="General_Aviation_3"  />
        <arc begin="148" end="0" isPushBackRoute="1" name="General_Aviation_3"  />
        <arc begin="148" end="36" isPushBackRoute="1" name="General_Aviation_3"  />
        <arc begin="36" end="148" isPushBackRoute="1" name="General_Aviation_3"  />
        <arc begin="1" end="149" isPushBackRoute="1" name="General_Aviation_6"  />
        <arc begin="149" end="1" isPushBackRoute="1" name="General_Aviation_6"  />
        <arc begin="149" end="38" isPushBackRoute="1" name="General_Aviation_6"  />
        <arc begin="38" end="149" isPushBackRoute="1" name="General_Aviation_6"  />
        <arc begin="2" end="150" isPushBackRoute="1" name="General_Aviation_6"  />
        <arc begin="150" end="2" isPushBackRoute="1" name="General_Aviation_6"  />
        <arc begin="150" end="39" isPushBackRoute="1" name="General_Aviation_6"  />
        <arc begin="39" end="150" isPushBackRoute="1" name="General_Aviation_6"  />
        <arc begin="3" end="151" isPushBackRoute="1" name="General_Aviation_5"  />
        <arc begin="151" end="3" isPushBackRoute="1" name="General_Aviation_5"  />
        <arc begin="151" end="100" isPushBackRoute="1" name="General_Aviation_5"  />
        <arc begin="100" end="151" isPushBackRoute="1" name="General_Aviation_5"  />
        <arc begin="4" end="152" isPushBackRoute="1" name="General_Aviation_4"  />
        <arc begin="152" end="4" isPushBackRoute="1" name="General_Aviation_4"  />
        <arc begin="152" end="36" isPushBackRoute="1" name="General_Aviation_4"  />
        <arc begin="36" end="152" isPushBackRoute="1" name="General_Aviation_4"  />
        <arc begin="5" end="153" isPushBackRoute="1" name="General_Aviation_2"  />
        <arc begin="153" end="5" isPushBackRoute="1" name="General_Aviation_2"  />
        <arc begin="153" end="37" isPushBackRoute="1" name="General_Aviation_2"  />
        <arc begin="37" end="153" isPushBackRoute="1" name="General_Aviation_2"  />
        <arc begin="6" end="154" isPushBackRoute="1" name="General_Aviation_1"  />
        <arc begin="154" end="6" isPushBackRoute="1" name="General_Aviation_1"  />
        <arc begin="154" end="36" isPushBackRoute="1" name="General_Aviation_1"  />
        <arc begin="36" end="154" isPushBackRoute="1" name="General_Aviation_1"  />
        <arc begin="7" end="155" isPushBackRoute="1" name="Gate_38"  />
        <arc begin="155" end="7" isPushBackRoute="1" name="Gate_38"  />
        <arc begin="155" end="64" isPushBackRoute="1" name="Gate_38"  />
        <arc begin="64" end="155" isPushBackRoute="1" name="Gate_38"  />
        <arc begin="8" end="156" isPushBackRoute="1" name="Gate_39"  />
        <arc begin="156" end="8" isPushBackRoute="1" name="Gate_39"  />
        <arc begin="156" end="65" isPushBackRoute="1" name="Gate_39"  />
        <arc begin="65" end="156" isPushBackRoute="1" name="Gate_39"  />
        <arc begin="9" end="157" isPushBackRoute="1" name="Gate_22"  />
        <arc begin="157" end="9" isPushBackRoute="1" name="Gate_22"  />
        <arc begin="157" end="88" isPushBackRoute="1" name="Gate_22"  />
        <arc begin="88" end="157" isPushBackRoute="1" name="Gate_22"  />
        <arc begin="10" end="158" isPushBackRoute="1" name="Gate_23"  />
        <arc begin="158" end="10" isPushBackRoute="1" name="Gate_23"  />
        <arc begin="158" end="49" isPushBackRoute="1" name="Gate_23"  />
        <arc begin="49" end="158" isPushBackRoute="1" name="Gate_23"  />
        <arc begin="11" end="159" isPushBackRoute="1" name="Gate_24"  />
        <arc begin="159" end="11" isPushBackRoute="1" name="Gate_24"  />
        <arc begin="159" end="48" isPushBackRoute="1" name="Gate_24"  />
        <arc begin="48" end="159" isPushBackRoute="1" name="Gate_24"  />
        <arc begin="12" end="160" isPushBackRoute="1" name="Gate_25"  />
        <arc begin="160" end="12" isPushBackRoute="1" name="Gate_25"  />
        <arc begin="160" end="47" isPushBackRoute="1" name="Gate_25"  />
        <arc begin="47" end="160" isPushBackRoute="1" name="Gate_25"  />
        <arc begin="13" end="161" isPushBackRoute="1" name="Gate_26"  />
        <arc begin="161" end="13" isPushBackRoute="1" name="Gate_26"  />
        <arc begin="161" end="46" isPushBackRoute="1" name="Gate_26"  />
        <arc begin="46" end="161" isPushBackRoute="1" name="Gate_26"  />
        <arc begin="14" end="162" isPushBackRoute="1" name="Gate_27"  />
        <arc begin="162" end="14" isPushBackRoute="1" name="Gate_27"  />
        <arc begin="162" end="45" isPushBackRoute="1" name="Gate_27"  />
        <arc begin="45" end="162" isPushBackRoute="1" name="Gate_27"  />
        <arc begin="15" end="163" isPushBackRoute="1" name="Gate_28"  />
        <arc begin="163" end="15" isPushBackRoute="1" name="Gate_28"  />
        <arc begin="163" end="44" isPushBackRoute="1" name="Gate_28"  />
        <arc begin="44" end="163" isPushBackRoute="1" name="Gate_28"  />
        <arc begin="16" end="164" isPushBackRoute="1" name="Gate_29"  />
        <arc begin="164" end="16" isPushBackRoute="1" name="Gate_29"  />
        <arc begin="164" end="50" isPushBackRoute="1" name="Gate_29"  />
        <arc begin="50" end="164" isPushBackRoute="1" name="Gate_29"  />
        <arc begin="17" end="165" isPushBackRoute="1" name="Gate_30"  />
        <arc begin="165" end="17" isPushBackRoute="1" name="Gate_30"  />
        <arc begin="165" end="93" isPushBackRoute="1" name="Gate_30"  />
        <arc begin="93" end="165" isPushBackRoute="1" name="Gate_30"  />
        <arc begin="18" end="166" isPushBackRoute="1" name="Gate_31"  />
        <arc begin="166" end="18" isPushBackRoute="1" name="Gate_31"  />
        <arc begin="166" end="94" isPushBackRoute="1" name="Gate_31"  />
        <arc begin="94" end="166" isPushBackRoute="1" name="Gate_31"  />
        <arc begin="19" end="167" isPushBackRoute="1" name="Gate_32"  />
        <arc begin="167" end="19" isPushBackRoute="1" name="Gate_32"  />
        <arc begin="167" end="95" isPushBackRoute="1" name="Gate_32"  />
        <arc begin="95" end="167" isPushBackRoute="1" name="Gate_32"  />
        <arc begin="20" end="168" isPushBackRoute="1" name="Gate_33"  />
        <arc begin="168" end="20" isPushBackRoute="1" name="Gate_33"  />
        <arc begin="168" end="96" isPushBackRoute="1" name="Gate_33"  />
        <arc begin="96" end="168" isPushBackRoute="1" name="Gate_33"  />
        <arc begin="21" end="169" isPushBackRoute="1" name="Gate_34"  />
        <arc begin="169" end="21" isPushBackRoute="1" name="Gate_34"  />
        <arc begin="169" end="97" isPushBackRoute="1" name="Gate_34"  />
        <arc begin="97" end="169" isPushBackRoute="1" name="Gate_34"  />
        <arc begin="22" end="170" isPushBackRoute="1" name="Gate_35"  />
        <arc begin="170" end="22" isPushBackRoute="1" name="Gate_35"  />
        <arc begin="170" end="98" isPushBackRoute="1" name="Gate_35"  />
        <arc begin="98" end="170" isPushBackRoute="1" name="Gate_35"  />
        <arc begin="23" end="171" isPushBackRoute="1" name="Gate_36"  />
        <arc begin="171" end="23" isPushBackRoute="1" name="Gate_36"  />
        <arc begin="171" end="99" isPushBackRoute="1" name="Gate_36"  />
        <arc begin="99" end="171" isPushBackRoute="1" name="Gate_36"  />
        <arc begin="24" end="172" isPushBackRoute="1" name="M6"  />
        <arc begin="172" end="24" isPushBackRoute="1" name="M6"  />
        <arc begin="172" end="84" isPushBackRoute="1" name="M6"  />
        <arc begin="84" end="172" isPushBackRoute="1" name="M6"  />
        <arc begin="25" end="173" isPushBackRoute="1" name="M5"  />
        <arc begin="173" end="25" isPushBackRoute="1" name="M5"  />
        <arc begin="173" end="76" isPushBackRoute="1" name="M5"  />
        <arc begin="76" end="173" isPushBackRoute="1" name="M5"  />
        <arc begin="26" end="174" isPushBackRoute="1" name="M4"  />
        <arc begin="174" end="26" isPushBackRoute="1" name="M4"  />
        <arc begin="174" end="82" isPushBackRoute="1" name="M4"  />
        <arc begin="82" end="174" isPushBackRoute="1" name="M4"  />
        <arc begin="27" end="175" isPushBackRoute="1" name="Gate_37"  />
        <arc begin="175" end="27" isPushBackRoute="1" name="Gate_37"  />
        <arc begin="175" end="87" isPushBackRoute="1" name="Gate_37"  />
        <arc begin="87" end="175" isPushBackRoute="1" name="Gate_37"  />
        <arc begin="28" end="176" isPushBackRoute="1" name="Gate_40"  />
        <arc begin="176" end="28" isPushBackRoute="1" name="Gate_40"  />
        <arc begin="176" end="102" isPushBackRoute="1" name="Gate_40"  />
        <arc begin="102" end="176" isPushBackRoute="1" name="Gate_40"  />
        <arc begin="29" end="177" isPushBackRoute="1" name="Gate_41"  />
        <arc begin="177" end="29" isPushBackRoute="1" name="Gate_41"  />
        <arc begin="177" end="73" isPushBackRoute="1" name="Gate_41"  />
        <arc begin="73" end="177" isPushBackRoute="1" name="Gate_41"  />
        <arc begin="30" end="178" isPushBackRoute="1" name="Gate_42"  />
        <arc begin="178" end="30" isPushBackRoute="1" name="Gate_42"  />
        <arc begin="178" end="72" isPushBackRoute="1" name="Gate_42"  />
        <arc begin="72" end="178" isPushBackRoute="1" name="Gate_42"  />
        <arc begin="31" end="179" isPushBackRoute="1" name="Gate_43"  />
        <arc begin="179" end="31" isPushBackRoute="1" name="Gate_43"  />
        <arc begin="179" end="71" isPushBackRoute="1" name="Gate_43"  />
        <arc begin="71" end="179" isPushBackRoute="1" name="Gate_43"  />
        <arc begin="32" end="180" isPushBackRoute="1" name="Gate_44"  />
        <arc begin="180" end="32" isPushBackRoute="1" name="Gate_44"  />
        <arc begin="180" end="70" isPushBackRoute="1" name="Gate_44"  />
        <arc begin="70" end="180" isPushBackRoute="1" name="Gate_44"  />
        <arc begin="33" end="181" isPushBackRoute="1" name="Gate_45"  />
        <arc begin="181" end="33" isPushBackRoute="1" name="Gate_45"  />
        <arc begin="181" end="69" isPushBackRoute="1" name="Gate_45"  />
        <arc begin="69" end="181" isPushBackRoute="1" name="Gate_45"  />
 </TaxiWaySegments>
</groundnet>
